kraken_image_processing/__init__.py
kraken_image_processing/class_imageObject.py
kraken_image_processing/class_person.py
kraken_image_processing/download_models.py
kraken_image_processing/flask_routes.py
kraken_image_processing/kraken_engine.py
kraken_image_processing/kraken_image_io.py
kraken_image_processing/kraken_image_processing.py
kraken_image_processing/post_to_image_share.py
kraken_image_processing/extractors/__init__.py
kraken_image_processing/extractors/kraken_image_face.py
kraken_image_processing/extractors/kraken_image_face_age.py
kraken_image_processing/extractors/kraken_image_face_embeddings.py
kraken_image_processing/extractors/kraken_image_face_emotions.py
kraken_image_processing/extractors/kraken_image_face_gender.py
kraken_image_processing/extractors/kraken_image_generic.py
kraken_image_processing/extractors/kraken_image_hash.py
kraken_image_processing/extractors/kraken_image_nude.py
kraken_image_processing/extractors/kraken_image_objects_temp.py
kraken_image_processing/extractors/kraken_image_person.py
kraken_image_processing/extractors/kraken_image_text.py
kraken_image_processing-0.0.24.dist-info/LICENSE.txt
kraken_image_processing-0.0.24.dist-info/METADATA
kraken_image_processing-0.0.24.dist-info/WHEEL
kraken_image_processing-0.0.24.dist-info/top_level.txt
kraken_image_processing-0.0.24.dist-info/RECORD
