Metadata-Version: 2.1
Name: kraken-image-processing
Version: 0.0.24
Summary: Kraken Image Processing
Home-page: https://github.com/tactik8/kraken_image_processing
Author: Tactik8
Author-email: info@tactik8.com
License: MIT
Classifier: License :: OSI Approved :: MIT License
Classifier: Programming Language :: Python :: 3
Classifier: Programming Language :: Python :: 3.8
License-File: LICENSE.txt
Requires-Dist: opencv-python-headless
Requires-Dist: fer
Requires-Dist: aiohttp
Requires-Dist: pyimgbox
Requires-Dist: kraken-class-entity
Requires-Dist: werkzeug
Requires-Dist: flask
Requires-Dist: pytesseract
